{"municipality":"飯舘村","pref":"福島県","muni_code":"074829","count":2,"items":[{"pref":"福島県","municipality":"飯舘村","name":"三匹獅子舞","category":"民俗文化財","subcategory":"無形民俗文化財","designation":"村指定","designated_date":null,"location":"比曽・草野地区","description":"五穀豊穣・悪霊退散を祈って奉納される三匹獅子舞。","source_url":"https://www.vill.iitate.fukushima.jp/site/kanko/74.html","source_format":"html","fetched_at":"2026-07-05T00:00:00+09:00","jmh_id":"JMH-074829-0001","en":{"name_romaji":"Sanbiki shishimai","romaji_confidence":"estimated","name_en":"Three-Lion Dance (Sanbiki Shishimai)","description_en":"Folk cultural property (intangible folk cultural property). Village-designated by Iitate Village. Located in the Hiso and Kusano districts."}},{"pref":"福島県","municipality":"飯舘村","name":"常念寺のイチョウ","category":"記念物(史跡・名勝・天然記念物)","subcategory":"天然記念物","designation":"村指定","designated_date":null,"location":"相馬郡飯舘村二枚橋字本町285（常念寺）","description":"樹齢約250年のイチョウ。福島県緑の文化財にも登録。","source_url":"https://www.vill.iitate.fukushima.jp/site/kanko/75.html","source_format":"html","fetched_at":"2026-07-05T00:00:00+09:00","jmh_id":"JMH-074829-0002","en":{"name_romaji":"Jōnenji no ichō","romaji_confidence":"estimated","name_en":"Ginkgo of Jonenji Temple","description_en":"Natural monument among the monuments (historic sites, places of scenic beauty and natural monuments). Village-designated by Iitate Village. Located at Aza Honmachi 285, Nimaibashi, Iitate Village, Soma District (Jonenji Temple)."}}]}