[
 {
  "jmh_id": "JMH-113611-0023",
  "name": "里宮の神楽",
  "category": "民俗文化財",
  "subcategory": "無形民俗文化財",
  "designation": "町指定",
  "designated_date": "1973-01-31",
  "municipality": "横瀬町",
  "location": "横瀬町大字横瀬879番地"
 },
 {
  "jmh_id": "JMH-113611-0014",
  "name": "札所五番語歌堂",
  "category": "記念物(史跡・名勝・天然記念物)",
  "subcategory": "記念物",
  "designation": "町指定",
  "designated_date": "1973-01-31",
  "municipality": "横瀬町",
  "location": "横瀬町大字横瀬6119番地"
 },
 {
  "jmh_id": "JMH-113611-0016",
  "name": "札所六番卜雲寺（荻野堂）",
  "category": "記念物(史跡・名勝・天然記念物)",
  "subcategory": "記念物",
  "designation": "町指定",
  "designated_date": "1973-01-31",
  "municipality": "横瀬町",
  "location": "横瀬町大字横瀬1430番地"
 },
 {
  "jmh_id": "JMH-113611-0012",
  "name": "札所七番法長寺（牛伏堂）",
  "category": "記念物(史跡・名勝・天然記念物)",
  "subcategory": "記念物",
  "designation": "町指定",
  "designated_date": "1973-01-31",
  "municipality": "横瀬町",
  "location": "横瀬町大字横瀬1508番地"
 },
 {
  "jmh_id": "JMH-113611-0015",
  "name": "札所八番西善寺",
  "category": "記念物(史跡・名勝・天然記念物)",
  "subcategory": "記念物",
  "designation": "町指定",
  "designated_date": "1973-01-31",
  "municipality": "横瀬町",
  "location": "横瀬町大字横瀬598番地"
 },
 {
  "jmh_id": "JMH-113611-0013",
  "name": "札所九番明智寺",
  "category": "記念物(史跡・名勝・天然記念物)",
  "subcategory": "記念物",
  "designation": "町指定",
  "designated_date": "1973-01-31",
  "municipality": "横瀬町",
  "location": "横瀬町大字横瀬2157番地"
 },
 {
  "jmh_id": "JMH-113611-0017",
  "name": "札所十番大慈寺",
  "category": "記念物(史跡・名勝・天然記念物)",
  "subcategory": "記念物",
  "designation": "町指定",
  "designated_date": "1973-01-31",
  "municipality": "横瀬町",
  "location": "横瀬町大字横瀬5151番地"
 },
 {
  "jmh_id": "JMH-113611-0018",
  "name": "根古屋城址",
  "category": "記念物(史跡・名勝・天然記念物)",
  "subcategory": "記念物",
  "designation": "町指定",
  "designated_date": "1973-01-31",
  "municipality": "横瀬町",
  "location": "横瀬町大字横瀬7926番地"
 },
 {
  "jmh_id": "JMH-113611-0007",
  "name": "古御嶽城址",
  "category": "記念物(史跡・名勝・天然記念物)",
  "subcategory": "記念物",
  "designation": "町指定",
  "designated_date": "1973-01-31",
  "municipality": "横瀬町",
  "location": "横瀬町大字横瀬8095番地1、他"
 },
 {
  "jmh_id": "JMH-113611-0022",
  "name": "追分の道標",
  "category": "記念物(史跡・名勝・天然記念物)",
  "subcategory": "記念物",
  "designation": "町指定",
  "designated_date": "1973-01-31",
  "municipality": "横瀬町",
  "location": "横瀬町大字芦ヶ久保1454番地　2"
 },
 {
  "jmh_id": "JMH-113611-0024",
  "name": "持山寺跡",
  "category": "記念物(史跡・名勝・天然記念物)",
  "subcategory": "記念物",
  "designation": "町指定",
  "designated_date": "1973-04-16",
  "municipality": "横瀬町",
  "location": "横瀬町大字横瀬8653番地"
 },
 {
  "jmh_id": "JMH-113611-0026",
  "name": "気楽流柔術家加藤良正の碑",
  "category": "記念物(史跡・名勝・天然記念物)",
  "subcategory": "記念物",
  "designation": "町指定",
  "designated_date": "1973-06-14",
  "municipality": "横瀬町",
  "location": "―"
 },
 {
  "jmh_id": "JMH-113611-0035",
  "name": "数術家加藤兼安の碑",
  "category": "記念物(史跡・名勝・天然記念物)",
  "subcategory": "記念物",
  "designation": "町指定",
  "designated_date": "1991-05-16",
  "municipality": "横瀬町",
  "location": "―"
 },
 {
  "jmh_id": "JMH-113611-0003",
  "name": "チチブベニシダレザクラ",
  "category": "記念物(史跡・名勝・天然記念物)",
  "subcategory": "記念物",
  "designation": "町指定",
  "designated_date": "1973-01-31",
  "municipality": "横瀬町",
  "location": "横瀬町大字横瀬2872番地1"
 },
 {
  "jmh_id": "JMH-113611-0001",
  "name": "ザゼンソウ自生地",
  "category": "記念物(史跡・名勝・天然記念物)",
  "subcategory": "記念物",
  "designation": "町指定",
  "designated_date": "1973-01-31",
  "municipality": "横瀬町",
  "location": "横瀬町大字芦ヶ久保1483番地1"
 },
 {
  "jmh_id": "JMH-113611-0002",
  "name": "ザゼンソウ自生地",
  "category": "記念物(史跡・名勝・天然記念物)",
  "subcategory": "記念物",
  "designation": "町指定",
  "designated_date": "1973-01-31",
  "municipality": "横瀬町",
  "location": "横瀬町大字芦ヶ久保1497番地5"
 },
 {
  "jmh_id": "JMH-113611-0030",
  "name": "大畑のカヤ",
  "category": "記念物(史跡・名勝・天然記念物)",
  "subcategory": "記念物",
  "designation": "町指定",
  "designated_date": "1988-03-25",
  "municipality": "横瀬町",
  "location": "横瀬町大字芦ヶ久保738番地"
 },
 {
  "jmh_id": "JMH-113611-0029",
  "name": "古峯神社のアカヤシオ自生地",
  "category": "記念物(史跡・名勝・天然記念物)",
  "subcategory": "記念物",
  "designation": "町指定",
  "designated_date": "1988-03-25",
  "municipality": "横瀬町",
  "location": "横瀬町大字芦ヶ久保1435番地"
 },
 {
  "jmh_id": "JMH-112381-0027",
  "name": "関口平太郎顕彰碑（芥川龍之介の撰文碑）",
  "category": "記念物(史跡・名勝・天然記念物)",
  "subcategory": "史跡",
  "designation": "市指定",
  "municipality": "蓮田市"
 },
 {
  "jmh_id": "JMH-112381-0021",
  "name": "綾瀬貝塚",
  "category": "記念物(史跡・名勝・天然記念物)",
  "subcategory": "史跡",
  "designation": "市指定",
  "municipality": "蓮田市"
 },
 {
  "jmh_id": "JMH-112381-0003",
  "name": "備前堤",
  "category": "記念物(史跡・名勝・天然記念物)",
  "subcategory": "史跡",
  "designation": "市指定",
  "municipality": "蓮田市"
 },
 {
  "jmh_id": "JMH-112381-0015",
  "name": "武州鉄道跡",
  "category": "記念物(史跡・名勝・天然記念物)",
  "subcategory": "史跡",
  "designation": "市指定",
  "municipality": "蓮田市"
 },
 {
  "jmh_id": "JMH-112381-0016",
  "name": "江ヶ崎城跡",
  "category": "記念物(史跡・名勝・天然記念物)",
  "subcategory": "史跡",
  "designation": "市指定",
  "municipality": "蓮田市"
 },
 {
  "jmh_id": "JMH-112381-0004",
  "name": "円空仏1",
  "category": "有形文化財",
  "subcategory": "彫刻",
  "designation": "市指定",
  "municipality": "蓮田市"
 },
 {
  "jmh_id": "JMH-112381-0005",
  "name": "円空仏2",
  "category": "有形文化財",
  "subcategory": "彫刻",
  "designation": "市指定",
  "municipality": "蓮田市"
 },
 {
  "jmh_id": "JMH-112381-0006",
  "name": "円空仏3",
  "category": "有形文化財",
  "subcategory": "彫刻",
  "designation": "市指定",
  "municipality": "蓮田市"
 },
 {
  "jmh_id": "JMH-112381-0033",
  "name": "黒浜久伊豆神社彫刻",
  "category": "有形文化財",
  "subcategory": "彫刻",
  "designation": "市指定",
  "municipality": "蓮田市"
 },
 {
  "jmh_id": "JMH-112381-0011",
  "name": "宝篋印塔",
  "category": "有形文化財",
  "subcategory": "歴史資料",
  "designation": "市指定",
  "municipality": "蓮田市"
 },
 {
  "jmh_id": "JMH-112381-0013",
  "name": "板石塔婆（通称「寅子石」）",
  "category": "有形文化財",
  "subcategory": "考古資料",
  "designation": "市指定",
  "municipality": "蓮田市"
 },
 {
  "jmh_id": "JMH-112381-0008",
  "name": "十三塚古墳出土遺物",
  "category": "有形文化財",
  "subcategory": "考古資料",
  "designation": "市指定",
  "municipality": "蓮田市"
 },
 {
  "jmh_id": "JMH-112381-0034",
  "name": "黒浜式土器1",
  "category": "有形文化財",
  "subcategory": "考古資料",
  "designation": "市指定",
  "municipality": "蓮田市"
 },
 {
  "jmh_id": "JMH-112381-0035",
  "name": "黒浜貝塚",
  "category": "記念物(史跡・名勝・天然記念物)",
  "subcategory": "史跡",
  "designation": "市指定",
  "municipality": "蓮田市"
 },
 {
  "jmh_id": "JMH-112381-0024",
  "name": "見沼代用水",
  "category": "記念物(史跡・名勝・天然記念物)",
  "subcategory": "史跡",
  "designation": "市指定",
  "municipality": "蓮田市"
 },
 {
  "jmh_id": "JMH-112381-0009",
  "name": "南朝銘の青石塔婆",
  "category": "有形文化財",
  "subcategory": "考古資料",
  "designation": "市指定",
  "municipality": "蓮田市"
 },
 {
  "jmh_id": "JMH-112381-0028",
  "name": "関山式土器1",
  "category": "有形文化財",
  "subcategory": "考古資料",
  "designation": "市指定",
  "municipality": "蓮田市"
 },
 {
  "jmh_id": "JMH-112381-0029",
  "name": "関山式土器2",
  "category": "有形文化財",
  "subcategory": "考古資料",
  "designation": "市指定",
  "municipality": "蓮田市"
 },
 {
  "jmh_id": "JMH-112381-0023",
  "name": "蓮田車站納地記念碑（蓮田車站記念碑）",
  "category": "記念物(史跡・名勝・天然記念物)",
  "subcategory": "史跡",
  "designation": "市指定",
  "municipality": "蓮田市"
 },
 {
  "jmh_id": "JMH-112381-0020",
  "name": "篠崎家文書",
  "category": "有形文化財",
  "subcategory": "古文書",
  "designation": "市指定",
  "municipality": "蓮田市"
 },
 {
  "jmh_id": "JMH-112381-0032",
  "name": "高虫氷川神社彫刻",
  "category": "有形文化財",
  "subcategory": "彫刻",
  "designation": "市指定",
  "municipality": "蓮田市"
 },
 {
  "jmh_id": "JMH-112381-0026",
  "name": "閏戸の式三番",
  "category": "無形文化財",
  "subcategory": "無形民俗文化財",
  "designation": "市指定",
  "municipality": "蓮田市"
 }
]